gconfid/__init__.py
gconfid-0.0.0.dist-info/METADATA
gconfid-0.0.0.dist-info/WHEEL
gconfid-0.0.0.dist-info/top_level.txt
gconfid-0.0.0.dist-info/RECORD
