Metadata-Version: 2.4
Name: gconfid
Version: 0.0.0
Summary: Coming soon ... G-Confid, Disclosure Avoidance Software from Statistics Canada.
Maintainer-email: "G-Confid Support, Statistics Canada" <statcan.gconfid-gconfid.statcan@statcan.gc.ca>
